JisuanjichengxuDeSiweiLuojiJavaMiaoshu/README.md
JisuanjichengxuDeSiweiLuojiJavaMiaoshu/__init__.py
JisuanjichengxuDeSiweiLuojiJavaMiaoshu/__main__.py
JisuanjichengxuDeSiweiLuojiJavaMiaoshu/file.epub
JisuanjichengxuDeSiweiLuojiJavaMiaoshu/index.html
JisuanjichengxuDeSiweiLuojiJavaMiaoshu/css/__init__.py
JisuanjichengxuDeSiweiLuojiJavaMiaoshu/css/annotations.css
JisuanjichengxuDeSiweiLuojiJavaMiaoshu/css/main.css
JisuanjichengxuDeSiweiLuojiJavaMiaoshu/css/normalize.css
JisuanjichengxuDeSiweiLuojiJavaMiaoshu/css/popup.css
JisuanjichengxuDeSiweiLuojiJavaMiaoshu/font/__init__.py
JisuanjichengxuDeSiweiLuojiJavaMiaoshu/font/fontello.eot
JisuanjichengxuDeSiweiLuojiJavaMiaoshu/font/fontello.svg
JisuanjichengxuDeSiweiLuojiJavaMiaoshu/font/fontello.ttf
JisuanjichengxuDeSiweiLuojiJavaMiaoshu/font/fontello.woff
JisuanjichengxuDeSiweiLuojiJavaMiaoshu/img/__init__.py
JisuanjichengxuDeSiweiLuojiJavaMiaoshu/img/annotator-glyph-sprite.png
JisuanjichengxuDeSiweiLuojiJavaMiaoshu/img/annotator-icon-sprite.png
JisuanjichengxuDeSiweiLuojiJavaMiaoshu/img/apple-touch-icon.png
JisuanjichengxuDeSiweiLuojiJavaMiaoshu/img/cancelfullscreen.png
JisuanjichengxuDeSiweiLuojiJavaMiaoshu/img/close.png
JisuanjichengxuDeSiweiLuojiJavaMiaoshu/img/fullscreen.png
JisuanjichengxuDeSiweiLuojiJavaMiaoshu/img/loader.gif
JisuanjichengxuDeSiweiLuojiJavaMiaoshu/img/menu-icon.png
JisuanjichengxuDeSiweiLuojiJavaMiaoshu/img/save.png
JisuanjichengxuDeSiweiLuojiJavaMiaoshu/img/saved.png
JisuanjichengxuDeSiweiLuojiJavaMiaoshu/img/settings-s.png
JisuanjichengxuDeSiweiLuojiJavaMiaoshu/img/settings.png
JisuanjichengxuDeSiweiLuojiJavaMiaoshu/img/star.png
JisuanjichengxuDeSiweiLuojiJavaMiaoshu/js/__init__.py
JisuanjichengxuDeSiweiLuojiJavaMiaoshu/js/epub.js
JisuanjichengxuDeSiweiLuojiJavaMiaoshu/js/epub.min.js
JisuanjichengxuDeSiweiLuojiJavaMiaoshu/js/epub.min.map
JisuanjichengxuDeSiweiLuojiJavaMiaoshu/js/hooks.min.js
JisuanjichengxuDeSiweiLuojiJavaMiaoshu/js/hooks.min.map
jisuanjichengxu_de_siwei_luoji_java_miaoshu-2024.3.2.0.dist-info/METADATA
jisuanjichengxu_de_siwei_luoji_java_miaoshu-2024.3.2.0.dist-info/WHEEL
jisuanjichengxu_de_siwei_luoji_java_miaoshu-2024.3.2.0.dist-info/entry_points.txt
jisuanjichengxu_de_siwei_luoji_java_miaoshu-2024.3.2.0.dist-info/top_level.txt
jisuanjichengxu_de_siwei_luoji_java_miaoshu-2024.3.2.0.dist-info/RECORD
